netoapi/__init__.py
netoapi/api_client.py
netoapi/api_session.py
netoapi/errors.py
netoapi-1.0.1.dist-info/LICENSE
netoapi-1.0.1.dist-info/METADATA
netoapi-1.0.1.dist-info/WHEEL
netoapi-1.0.1.dist-info/top_level.txt
netoapi-1.0.1.dist-info/RECORD
